json_rule_engine/__init__.py
json_rule_engine/builder.py
json_rule_engine/core.py
json_rule_engine/django_q.py
json_rule_engine/evaluator.py
json_rule_engine-2.1.0.dist-info/licenses/LICENSE
json_rule_engine-2.1.0.dist-info/METADATA
json_rule_engine-2.1.0.dist-info/WHEEL
json_rule_engine-2.1.0.dist-info/top_level.txt
json_rule_engine-2.1.0.dist-info/RECORD
