Metadata-Version: 2.4
Name: json-rule-engine
Version: 2.1.0
Summary: A lightweight library for building, evaluating, and translating JSON-based rules
Home-page: https://github.com/anandabehera/json-rule-engine
Author: Ananda Behera
Author-email: Ananda Behera <behera.anand1@gmail.com>, Ananda Behera <ananda@callhub.io>
Maintainer-email: Ananda Behera <behera.anand1@gmail.com>, Ananda Behera <ananda@callhub.io>
License: MIT
Project-URL: Homepage, https://github.com/ananda-callhub/json-q-engine
Project-URL: Documentation, https://json-rule-engine.readthedocs.io
Project-URL: Repository, https://github.com/ananda-callhub/json-q-engine
Project-URL: Issues, https://github.com/ananda-callhub/json-q-engine/issues
Keywords: json,rules,rule-engine,jsonlogic,django,query,filter,evaluation,business-rules
Classifier: Development Status :: 4 - Beta
Classifier: Intended Audience :: Developers
Classifier: Topic :: Software Development :: Libraries :: Python Modules
Classifier: License :: OSI Approved :: MIT License
Classifier: Programming Language :: Python :: 3
Classifier: Programming Language :: Python :: 3.8
Classifier: Programming Language :: Python :: 3.9
Classifier: Programming Language :: Python :: 3.10
Classifier: Programming Language :: Python :: 3.11
Classifier: Programming Language :: Python :: 3.12
Classifier: Operating System :: OS Independent
Classifier: Framework :: Django
Requires-Python: >=3.8
License-File: LICENSE
Provides-Extra: django
Requires-Dist: django>=3.2; extra == "django"
Provides-Extra: dev
Requires-Dist: pytest>=7.0; extra == "dev"
Requires-Dist: pytest-cov>=4.0; extra == "dev"
Requires-Dist: black>=22.0; extra == "dev"
Requires-Dist: flake8>=5.0; extra == "dev"
Requires-Dist: mypy>=0.990; extra == "dev"
Requires-Dist: isort>=5.10; extra == "dev"
Provides-Extra: docs
Requires-Dist: sphinx>=5.0; extra == "docs"
Requires-Dist: sphinx-rtd-theme>=1.0; extra == "docs"
Provides-Extra: all
Requires-Dist: django>=3.2; extra == "all"
Requires-Dist: pytest>=7.0; extra == "all"
Requires-Dist: pytest-cov>=4.0; extra == "all"
Requires-Dist: black>=22.0; extra == "all"
Requires-Dist: flake8>=5.0; extra == "all"
Requires-Dist: mypy>=0.990; extra == "all"
Requires-Dist: isort>=5.10; extra == "all"
Requires-Dist: sphinx>=5.0; extra == "all"
Requires-Dist: sphinx-rtd-theme>=1.0; extra == "all"
Dynamic: author
Dynamic: home-page
Dynamic: license-file
Dynamic: requires-python
